test/tests.py
test/__init__.py
RandomWords-0.1.12.dist-info/WHEEL
RandomWords-0.1.12.dist-info/top_level.txt
RandomWords-0.1.12.dist-info/METADATA
RandomWords-0.1.12.dist-info/pydist.json
RandomWords-0.1.12.dist-info/DESCRIPTION.rst
RandomWords-0.1.12.dist-info/RECORD
random_words/lorem_ipsum.py
random_words/dmails.dat
random_words/nouns.dat
random_words/lorem_ipsum.dat
random_words/nicknames.dat
random_words/random_words.py
random_words/__init__.py
random_words/test/tests.py
random_words/test/__init__.py
