Metadata-Version: 1.1
Name: RandomWords
Version: 0.1.12
Summary: A useful module for a random text, e-mails and lorem ipsum.
Home-page: https://github.com/tomislater/RandomWords
Author: Tomek Święcicki
Author-email: tomislater@gmail.com
License: LICENSE.txt
Platform: UNKNOWN
Classifier: Intended Audience :: Developers
Classifier: License :: OSI Approved :: MIT License
Classifier: Programming Language :: Python
Classifier: Natural Language :: English
Classifier: Development Status :: 5 - Production/Stable
Classifier: Programming Language :: Python :: 2.6
Classifier: Programming Language :: Python :: 2.7
Classifier: Programming Language :: Python :: 3.2
Classifier: Programming Language :: Python :: 3.3
Classifier: Topic :: Software Development :: Libraries :: Python Modules
